create_st/cli.py
create_st/init.py
create_st/parser.py
create_st-0.1.6.dist-info/METADATA
create_st-0.1.6.dist-info/WHEEL
create_st-0.1.6.dist-info/entry_points.txt
create_st-0.1.6.dist-info/top_level.txt
create_st-0.1.6.dist-info/RECORD
