Metadata-Version: 2.4
Name: create-st
Version: 0.1.6
Summary: CLI tool for generating directory structures from a text file
Author: aloha v2
Requires-Python: >=3.7
